README.md
setup.cfg
setup.py
run_jnb/__init__.py
run_jnb/core.py
run_jnb/jnb_helper.py
run_jnb/run_jnb.py
run_jnb/util.py
run_jnb.egg-info/PKG-INFO
run_jnb.egg-info/SOURCES.txt
run_jnb.egg-info/dependency_links.txt
run_jnb.egg-info/entry_points.txt
run_jnb.egg-info/requires.txt
run_jnb.egg-info/top_level.txt