Metadata-Version: 1.2
Name: run-jnb
Version: 0.1.11
Summary: Parametrise (python3 only) and execute Jupyter notebooks
Home-page: https://github.com/hz-inova/run_jnb
Author: Andrei V. Plamada
Author-email: andreiplamada@gmail.com
License: BSD 3-clause "New" or "Revised" License
Keywords: jupyter-notebook,execute,parametrise
Platform: UNKNOWN
Classifier: Development Status :: 3 - Alpha
Classifier: License :: OSI Approved :: BSD License
Requires-Python: >=3.5
